mighty_logger/__init__.py
mighty_logger/mighty_logger.py
mighty_logger/simple_logger.py
mighty_logger/basic/__init__.py
mighty_logger/basic/basic_logger.py
mighty_logger/basic/exceptions.py
mighty_logger/basic/exporter.py
mighty_logger/basic/modifier.py
mighty_logger/basic/singleton.py
mighty_logger/basic/text_buffer.py
mighty_logger/basic/lib_types/__init__.py
mighty_logger/basic/lib_types/animation_type.py
mighty_logger/basic/lib_types/entry_type.py
mighty_logger/basic/lib_types/environment_type.py
mighty_logger/basic/lib_types/sorting_key_type.py
mighty_logger/basic/lib_types/text_buffer_type.py
mighty_logger/src/__init__.py
mighty_logger/src/animations.py
mighty_logger/src/ansi_format.py
mighty_logger/src/color_picker.py
mighty_logger/src/entry_types.py
mighty_logger/src/environments.py
mighty_logger/src/sorting_keys.py
mighty_logger-1.0.0.dist-info/LICENSE
mighty_logger-1.0.0.dist-info/METADATA
mighty_logger-1.0.0.dist-info/WHEEL
mighty_logger-1.0.0.dist-info/top_level.txt
mighty_logger-1.0.0.dist-info/RECORD
