Metadata-Version: 2.1
Name: mighty-logger
Version: 1.0.0
Summary: Mighty functional logger
Author-email: Kalynovsky 'Nakamura Akira' Valentin <nakama3942@gmail.com>
License: Apache License Version 2.0
Project-URL: Repository, https://github.com/Nakama3942/mighty_logger
Project-URL: Releases, https://github.com/Nakama3942/mighty_logger/releases
Classifier: Development Status :: 5 - Production/Stable
Classifier: Intended Audience :: Developers
Classifier: License :: OSI Approved :: Apache Software License
Classifier: Operating System :: OS Independent
Classifier: Programming Language :: Python :: 3.11
Classifier: Topic :: System :: Logging
Requires-Python: >=3.11
License-File: LICENSE
